{
  "id": "troika-ko",
  "title": "Troika! (한국어)",
  "description": "Fan-made Foundry VTT system for 'Troika!' The system is an independent production by author(s), and is not affiliated with the Melsonian Arts Council.",
  "url": "https://github.com/TheLastScrub/troika-foundry-vtt-system-unofficial",
  "license": "LICENSE.txt",
  "background": "systems/troika/assets/troika-compatibility-logo-splash-page.webp",
  "authors": [
    {
      "name": "vedmin",
      "discord": "vedmin_studen"
    }    
  ],
  "version": "1.1.8",
  "compatibility": {
    "minimum": "11",
    "verified": "11"
  },
  "manifest": "https://raw.githubusercontent.com/VedminStuden/fvtt-troika-ko/main/system.json",
  "download": "https://github.com/VedminStuden/fvtt-troika-ko/archive/refs/heads/main.zip",
  "gridDistance": 1,
  "gridUnits": "m",
  "primaryTokenAttribute": "stamina",
  "secondaryTokenAttribute": "luck",
  "esmodules": [
    "module/troika.js"
  ],
  "styles": [
    "css/troika.css"
  ],
  "languages": [
  ],
  "packs": [
    {
      "name": "troika-srd-spells",
      "label": "트로이카 SRD 주문",
      "system": "troika",
      "path": "packs/troika-srd-spells",
      "private": false,
      "type": "Item",
      "flags": {}
    },
    {
      "name": "troika-srd-roll-tables",
      "label": "트로이카 SRD 랜덤 테이블",
      "system": "troika",
      "path": "packs/troika-srd-roll-tables",
      "private": false,
      "type": "RollTable",
      "flags": {}
    },
    {
      "name": "troika-srd-weapons",
      "label": "트로이카 SRD 무기와 공격",
      "system": "troika",
      "path": "packs/troika-srd-weapons-and-attacks",
      "private": false,
      "type": "Item",
      "flags": {}
    },
    {
      "name": "troika-srd-skills",
      "label": "트로이카 SRD 기술",
      "system": "troika",
      "path": "packs/troika-srd-skills",
      "private": false,
      "type": "Item",
      "flags": {}
    },
    {
      "name": "troika-srd-items",
      "label": "트로이카 SRD 아이템",
      "system": "troika",
      "path": "packs/troika-srd-items",
      "private": false,
      "type": "Item",
      "flags": {}
    },
    {
      "name": "troika-srd-backgrounds",
      "label": "트로이카 SRD 배경",
      "system": "troika",
      "path": "packs/troika-srd-backgrounds",
      "private": false,
      "type": "Actor",
      "flags": {}
    },
    {
      "name": "troika-bat-npc",
      "label": "트로이카 bat npc",
      "system": "troika",
      "path": "packs/troika-bat-npc",
      "private": false,
      "type": "Actor",
      "flags": {}
    },
    {
      "name": "troika-bat-rule",
      "label": "트로이카 룰 및 모듈",
      "system": "troika",
      "path": "packs/troika-bat-rule",
      "private": false,
      "type": "JournalEntry",
      "flags": {}
    },
    {
      "name": "troika-bat-scene",
      "label": "트로이카 bat 장면",
      "system": "troika",
      "path": "packs/troika-bat-scene",
      "private": false,
      "type": "Scene",
      "flags": {}
    }
  ]
}
